LICENSE
README.md
pyproject.toml
setup.cfg
setup.py
ambient/__init__.py
ambient/createAutoAmbient.py
ambient/createTagsFile.py
ambient/getFile.py
ambient/models/blocksModel.py
ambient/models/mainModel.py
ambient/models/runModel.py
ambient/tolls/clicks.py
ambient/tolls/gui.py
ambient/tolls/utils.py
autoAmbient.egg-info/PKG-INFO
autoAmbient.egg-info/SOURCES.txt
autoAmbient.egg-info/dependency_links.txt
autoAmbient.egg-info/entry_points.txt
autoAmbient.egg-info/requires.txt
autoAmbient.egg-info/top_level.txt