Metadata-Version: 2.1
Name: autoAmbient
Version: 0.4.1
Summary: UNKNOWN
Home-page: https://github.com/luisArthurRodriguesDaSilva/automations-enviroment
Author: Luis Arthur Rodrigues da Silva
Author-email: luisarthurlards03@gmail.com
License: MIT
Platform: UNKNOWN
Requires-Python: >=3.8
